music_browser/__init__.py
music_browser/browser.py
music_browser/exceptions.py
music_browser/metadata.py
music_browser/serializer.py
music_browser/models/__init__.py
music_browser/models/simple_track.py
music_browser/plugins/__init__.py
music_browser/plugins/base.py
music_browser/plugins/deezer.py
music_browser/plugins/spotify.py
music_browser-0.0.4.dist-info/LICENSE
music_browser-0.0.4.dist-info/METADATA
music_browser-0.0.4.dist-info/WHEEL
music_browser-0.0.4.dist-info/top_level.txt
music_browser-0.0.4.dist-info/RECORD
