Metadata-Version: 2.1
Name: music-browser
Version: 0.0.4
Summary: Music search engine for CrossPlay web service.
Home-page: https://github.com/tms-studio/python-music-browser
Author: Sylvan Le Deunff
Author-email: sledeunf@gmail.com
License: UNKNOWN
Platform: UNKNOWN
Classifier: Intended Audience :: Developers
Classifier: Operating System :: MacOS :: MacOS X
Classifier: Operating System :: Microsoft :: Windows
Classifier: Operating System :: POSIX
Classifier: Programming Language :: Python
Requires-Dist: marshmallow
Requires-Dist: requests
